furlong/__about__.py
furlong/__init__.py
furlong-0.0.1.dist-info/METADATA
furlong-0.0.1.dist-info/WHEEL
furlong-0.0.1.dist-info/entry_points.txt
furlong-0.0.1.dist-info/license_files/LICENSE.txt
furlong-0.0.1.dist-info/RECORD
